travis-0.0.2.dist-info/metadata.json
travis-0.0.2.dist-info/top_level.txt
travis-0.0.2.dist-info/METADATA
travis-0.0.2.dist-info/DESCRIPTION.rst
travis-0.0.2.dist-info/entry_points.txt
travis-0.0.2.dist-info/RECORD
travis-0.0.2.dist-info/WHEEL
travis/__init__.py
